cp77_hairdresser/__init__.py
cp77_hairdresser/editor.py
cp77_hairdresser/editor_gui.py
cp77_hairdresser/hairstyles.json
cp77_hairdresser/json2obj.py
cp77_hairdresser/ui/editor.ui
cp77_hairdresser/ui/resource.qrc
cp77_hairdresser/ui/images/female/female01.png
cp77_hairdresser/ui/images/female/female02.png
cp77_hairdresser/ui/images/female/female03.png
cp77_hairdresser/ui/images/female/female04.png
cp77_hairdresser/ui/images/female/female05.png
cp77_hairdresser/ui/images/female/female06.png
cp77_hairdresser/ui/images/female/female07.png
cp77_hairdresser/ui/images/female/female08.png
cp77_hairdresser/ui/images/female/female09.png
cp77_hairdresser/ui/images/female/female10.png
cp77_hairdresser/ui/images/female/female11.png
cp77_hairdresser/ui/images/female/female12.png
cp77_hairdresser/ui/images/female/female13.png
cp77_hairdresser/ui/images/female/female14.png
cp77_hairdresser/ui/images/female/female15.png
cp77_hairdresser/ui/images/female/female16.png
cp77_hairdresser/ui/images/female/female17.png
cp77_hairdresser/ui/images/female/female18.png
cp77_hairdresser/ui/images/female/female19.png
cp77_hairdresser/ui/images/female/female20.png
cp77_hairdresser/ui/images/female/female21.png
cp77_hairdresser/ui/images/female/female22.png
cp77_hairdresser/ui/images/female/female23.png
cp77_hairdresser/ui/images/female/female24.png
cp77_hairdresser/ui/images/female/female25.png
cp77_hairdresser/ui/images/female/female26.png
cp77_hairdresser/ui/images/female/female27.png
cp77_hairdresser/ui/images/female/female28.png
cp77_hairdresser/ui/images/female/female29.png
cp77_hairdresser/ui/images/female/female30.png
cp77_hairdresser/ui/images/female/female31.png
cp77_hairdresser/ui/images/female/female32.png
cp77_hairdresser/ui/images/female/female33.png
cp77_hairdresser/ui/images/female/female34.png
cp77_hairdresser/ui/images/female/female35.png
cp77_hairdresser/ui/images/female/female36.png
cp77_hairdresser/ui/images/female/female37.png
cp77_hairdresser/ui/images/female/female38.png
cp77_hairdresser-0.1.1.dist-info/METADATA
cp77_hairdresser-0.1.1.dist-info/WHEEL
cp77_hairdresser-0.1.1.dist-info/top_level.txt
cp77_hairdresser-0.1.1.dist-info/RECORD
