Metadata-Version: 2.1
Name: cp77-hairdresser
Version: 0.1.1
Summary: Cyberpunk 2077 hairstyle changer
Home-page: https://github.com/eVen-gits/cp77_hairdresser
Author: Egej Vencelj
Author-email: egej.vencelj@gmail.com
License: UNKNOWN
Platform: UNKNOWN
Classifier: Programming Language :: Python :: 3
Classifier: License :: OSI Approved :: MIT License
Classifier: Operating System :: OS Independent
Requires-Python: >=3.6
Requires-Dist: pyqt5
